{"cameraMode":{"drawMode":0,"name":"Shaded","section":"Shading Mode"},"sceneLighting":true,"audioPlay":false,"sceneViewState":{"showFog":true,"showMaterialUpdate":false,"showSkybox":true,"showFlares":true,"showImageEffects":true,"showParticleSystems":true},"in2DMode":false,"pivot":{"x":38.56132507324219,"y":-96.62224578857422,"z":162.50592041015626},"rotation":{"x":0.3346390128135681,"y":-0.029677193611860277,"z":0.010544548742473126,"w":0.9418210387229919},"size":331.4380187988281,"orthographic":false}